executor/__init__.py
executor/app.py
executor/executor.py
executor/httpservice.py
executor/job.py
executor/notifier.py
executor/scheduler.py
yqg_py_scheduler-0.1.4.dist-info/METADATA
yqg_py_scheduler-0.1.4.dist-info/WHEEL
yqg_py_scheduler-0.1.4.dist-info/top_level.txt
yqg_py_scheduler-0.1.4.dist-info/RECORD
